huggingface_hub_storj_patch.py
huggingface_hub_storj_patch-0.0.6.dist-info/LICENSE
huggingface_hub_storj_patch-0.0.6.dist-info/METADATA
huggingface_hub_storj_patch-0.0.6.dist-info/WHEEL
huggingface_hub_storj_patch-0.0.6.dist-info/top_level.txt
huggingface_hub_storj_patch-0.0.6.dist-info/RECORD
