Metadata-Version: 2.1
Name: huggingface-hub-storj-patch
Version: 0.0.6
Summary: Monkey patch for huggingface_hub to download Git-LFS blobs from Storj
Home-page: https://github.com/storj/huggingface-hub-storj-patch
Author: Kaloyan Raev
Author-email: kaloyan@storj.io
License: Apache
Keywords: model-hub machine-learning models natural-language-processing deep-learning pytorch pretrained-models storj patch linksharing decentralized cloud storage
Classifier: Intended Audience :: Developers
Classifier: Intended Audience :: Education
Classifier: Intended Audience :: Science/Research
Classifier: License :: OSI Approved :: Apache Software License
Classifier: Operating System :: OS Independent
Classifier: Programming Language :: Python :: 3
Classifier: Programming Language :: Python :: 3 :: Only
Classifier: Programming Language :: Python :: 3.7
Classifier: Programming Language :: Python :: 3.8
Classifier: Programming Language :: Python :: 3.9
Classifier: Programming Language :: Python :: 3.10
Classifier: Programming Language :: Python :: 3.11
Classifier: Topic :: Scientific/Engineering :: Artificial Intelligence
Requires-Python: >=3.7.0
License-File: LICENSE
Requires-Dist: huggingface-hub (>=0.13)
